pymicropel/__init__.py
pymicropel/communicator/__init__.py
pymicropel/communicator/abstract_communicator.py
pymicropel/communicator/mpc_300.py
pymicropel/communicator/mpc_400.py
pymicropel/communicator/tcp_client.py
pymicropel/epnp/__init__.py
pymicropel/epnp/epnp.py
pymicropel/helper/__init__.py
pymicropel/helper/convert.py
pymicropel/helper/crc.py
pymicropel/helper/crypto.py
pymicropel/helper/exceptions.py
pymicropel/helper/message.py
pymicropel/test/__init__.py
pymicropel/test/test_helper/__init__.py
pymicropel/test/test_helper/test_convert.py
pymicropel/test/test_helper/test_crc.py
pymicropel/test/test_helper/test_crypto.py
pymicropel/test/test_helper/test_message.py
pymicropel-1.0.1.dist-info/LICENSE
pymicropel-1.0.1.dist-info/METADATA
pymicropel-1.0.1.dist-info/WHEEL
pymicropel-1.0.1.dist-info/top_level.txt
pymicropel-1.0.1.dist-info/RECORD
