Metadata-Version: 2.1
Name: pymicropel
Version: 1.0.1
Summary: Python library for communication with Micropel PLC.
Home-page: UNKNOWN
Author: Vladislav Korecky
Author-email: <vladislav@korecky.org>
License: UNKNOWN
Keywords: python,plc,tcp_ip,communication,iot,automation
Platform: UNKNOWN
Classifier: Development Status :: 5 - Production/Stable
Classifier: Intended Audience :: Developers
Classifier: Programming Language :: Python :: 3
Classifier: Operating System :: Unix
Classifier: Operating System :: MacOS :: MacOS X
Classifier: Operating System :: Microsoft :: Windows
License-File: LICENSE
